extract_emails/__init__.py
extract_emails/browsers/__init__.py
extract_emails/browsers/chromium_browser.py
extract_emails/browsers/httpx_browser.py
extract_emails/browsers/page_source_getter.py
extract_emails/console/__init__.py
extract_emails/console/application.py
extract_emails/data_extractors/__init__.py
extract_emails/data_extractors/data_extractor.py
extract_emails/data_extractors/email_extractor.py
extract_emails/data_extractors/linkedin_extractor.py
extract_emails/data_savers/__init__.py
extract_emails/data_savers/csv_saver.py
extract_emails/data_savers/data_saver.py
extract_emails/errors/__init__.py
extract_emails/errors/errors.py
extract_emails/link_filters/__init__.py
extract_emails/link_filters/contact_link_filter.py
extract_emails/link_filters/default_link_filter.py
extract_emails/link_filters/link_filter_base.py
extract_emails/models/__init__.py
extract_emails/models/page_data.py
extract_emails/utils/__init__.py
extract_emails/utils/_top_level_domains.py
extract_emails/utils/email_filter.py
extract_emails/workers/__init__.py
extract_emails/workers/default_worker.py
extract_emails-6.0.1.dist-info/METADATA
extract_emails-6.0.1.dist-info/WHEEL
extract_emails-6.0.1.dist-info/entry_points.txt
extract_emails-6.0.1.dist-info/licenses/LICENSE
extract_emails-6.0.1.dist-info/RECORD
