Metadata-Version: 2.4
Name: extract-emails
Version: 6.0.1
Summary: Extract email addresses and linkedin profiles from given URL.
Project-URL: repository, https://github.com/dmitriiweb/extract-emails
Project-URL: documentation, https://dmitriiweb.github.io/extract-emails
Author-email: Dmitrii K <dmitriik@proton.me>
License-File: LICENSE
Keywords: email,linkedin,parser
Classifier: Development Status :: 5 - Production/Stable
Classifier: License :: OSI Approved :: MIT License
Classifier: Operating System :: MacOS
Classifier: Operating System :: Microsoft :: Windows
Classifier: Operating System :: Unix
Classifier: Programming Language :: Python :: 3.10
Classifier: Programming Language :: Python :: 3.11
Classifier: Programming Language :: Python :: 3.12
Classifier: Programming Language :: Python :: 3.13
Classifier: Programming Language :: Python :: Implementation :: CPython
Classifier: Topic :: Utilities
Requires-Python: <3.14,>=3.10
Requires-Dist: aiocsv>=1.3.2
Requires-Dist: aiofiles>=24.1.0
Requires-Dist: loguru>=0.7.3
Requires-Dist: pydantic>=2.11.7
Provides-Extra: all
Requires-Dist: httpx>=0.28.1; extra == 'all'
Requires-Dist: playwright>=1.52.0; extra == 'all'
Provides-Extra: dev
Requires-Dist: jinja2>=3.1.6; extra == 'dev'
Requires-Dist: mkdocs-autorefs>=1.4.2; extra == 'dev'
Requires-Dist: mkdocs-copy-to-llm>=0.2.6; extra == 'dev'
Requires-Dist: mkdocs-material>=9.6.14; extra == 'dev'
Requires-Dist: mkdocs>=1.6.1; extra == 'dev'
Requires-Dist: mkdocstrings[python]>=0.29.1; extra == 'dev'
Requires-Dist: mypy>=1.16.1; extra == 'dev'
Requires-Dist: pygments>=2.19.1; extra == 'dev'
Requires-Dist: pytest-async>=0.1.1; extra == 'dev'
Requires-Dist: pytest-asyncio>=1.3.0; extra == 'dev'
Requires-Dist: pytest-cov>=6.2.1; extra == 'dev'
Requires-Dist: pytest>=8.4.1; extra == 'dev'
Requires-Dist: ruff>=0.12.0; extra == 'dev'
Requires-Dist: tox>=4.27.0; extra == 'dev'
Provides-Extra: httpx
Requires-Dist: httpx>=0.28.1; extra == 'httpx'
Provides-Extra: playwright
Requires-Dist: playwright>=1.52.0; extra == 'playwright'
